{
  "name": "Base2Tone-Pool",
  "type": "dark",
  "colorscheme made by": "by Bram de Haan, adapted from DuoTone themes by Simurai (http://simurai.com/projects/2016/01/01/duotone-themes)",
  "repository": "https://github.com/atelierbram/Base2Tone-VSCode-Themes",
  "tokenColors": [
    {
      "settings": {
        "background": "#2a2433",
        "foreground": "#afa7b9",
        "fontStyle": "italic"
      }
    },
    {
      "scope": ["meta.embedded", "source.groovy.embedded"],
      "settings": {
        "background": "#2a2433",
        "foreground": "#afa7b9"
      }
    },
    {
      "name": "Comment",
      "scope": [
        "comment",
        "punctuation.definition.comment"
      ],
      "settings": {
        "fontStyle": "italic",
        "foreground": "#574b68"
      }
    },
    {
      "name": "Variables",
      "scope": [
        "variable",
        "string constant.other.placeholder"
      ],
      "settings": {
        "foreground": "#8f51e6"
      }
    },
    {
      "name": "Colors",
      "scope": [
        "constant.other.color"
      ],
      "settings": {
        "foreground": "#f3ebff"
      }
    },
    {
      "name": "Invalid",
      "scope": [
        "invalid",
        "invalid.illegal"
      ],
      "settings": {
        "foreground":  "#f3ebff"
      }
    },
    {
      "name": "Keyword, Storage",
      "scope": [
        "keyword",
        "punctuation.accessor",
        "storage.type"
      ],
      "settings": {
        "foreground": "#ffb6b3"
      }
    },
    {
      "name": "Keyword, Storage",
      "scope": [
        "storage.modifier",
        "constant.keyword.clojure"
      ],
      "settings": {
        "foreground": "#ed655e"
      }
    },
    {
      "name": "Operator, Misc",
      "scope": [
        "punctuation",
        "punctuation.definition.tag",
        "punctuation.separator.inheritance.php",
        "punctuation.definition.tag.html",
        "punctuation.definition.tag.begin.html",
        "punctuation.definition.tag.end.html",
        "punctuation.section.embedded",
        "meta.function punctuation.separator.comma",
        "punctuation.definition.string",
        "punctuation.definition.parameters",
        "punctuation.terminator.expression",
        "punctuation.definition.arguments",
        "punctuation.definition.array",
        "punctuation.section.array",
        "punctuation.definition.list.begin",
        "punctuation.definition.list.end",
        "punctuation.separator.arguments",
        "punctuation.definition.list",
        "meta.array" ,
        "source.elixir punctuation.definition.string",
        "string.quoted.double.json punctuation.definition.string.json"
      ],
      "settings": {
        "foreground": "#635775"
      }
    },
    {
      "name": "Operator, Misc",
      "scope": [
        "keyword.control",
        "constant.other.color",
        "keyword.other.template",
        "keyword.other.substitution"
      ],
      "settings": {
        "foreground": "#fc8983"
      }
    },
    {
      "name": "Tag",
      "scope": [
        "entity.name.tag",
        "meta.tag.sgml",
        "markup.deleted.git_gutter"
      ],
      "settings": {
        "foreground": "#8f51e6"
      }
    },
    {
      "name": "Function, Special Method",
      "scope": [
        "meta.function-call",
        "variable.function",
        "support.function",
        "keyword.other.debugger",
        "keyword.other.special-method",
        "entity.name.function.clojure"
      ],
      "settings": {
        "foreground": "#f3ebff"
      }
    },
    {
      "name": "Block Level Variables",
      "scope": [
        "meta.block variable.other"
      ],
      "settings": {
        "foreground": "#afa7b9"
      }
    },
    {
      "name": "Other Variable, String Link",
      "scope": [
        "support.other.variable",
        "string.other.link"
      ],
      "settings": {
        "foreground": "#ffb6b3"
      }
    },
    {
      "name": "Number, Constant, Function Argument, Tag Attribute, Embedded",
      "scope": [
        "constant.language",
        "support.constant",
        "constant.character",
        "constant.escape",
        "keyword.other.unit",
        "keyword.other"
      ],
      "settings": {
        "foreground": "#ff9e99"
      }
    },
    {
      "name": "String, Symbols, Inherited Class, Markup Heading",
      "scope": [
        "constant.other.symbol",
        "constant.other.key",
        "entity.other.inherited-class",
        "markup.heading",
        "markup.inserted.git_gutter",
        "meta.group.braces.curly constant.other.object.key.js string.unquoted.label.js"
      ],
      "settings": {
        "fontStyle": "normal",
        "foreground": "#aa75f5"
      }
    },
    {
      "name": "Class, Support",
      "scope": [
        "entity.name",
        "support.type",
        "support.class",
        "support.orther.namespace.use.php",
        "meta.use.php",
        "support.other.namespace.php",
        "markup.changed.git_gutter",
        "support.type.sys-types"
      ],
      "settings": {
        "foreground": "#9f9393"
      }
    },
    {
      "name": "Entity Types",
      "scope": [
        "support.type"
      ],
      "settings": {
        "foreground": "#f87972"
      }
    },
    {
      "name": "CSS Class and Support",
      "scope": [
        "source.css support.type.property-name",
        "source.sass support.type.property-name",
        "source.scss support.type.property-name",
        "source.less support.type.property-name",
        "source.stylus support.type.property-name",
        "source.postcss support.type.property-name"
      ],
      "settings": {
        "foreground": "#c7a0fe"
      }
    },
    {
      "name": "Sub-methods JS",
      "scope": [
        "entity.name.module.js",
        "variable.import.parameter.js",
        "variable.other.class.js"
      ],
      "settings": {
        "foreground": "#8f51e6"
      }
    },
    {
      "name": "Sub-methods PHP",
      "scope": "variable.other.global.safer.php",
      "settings": {
        "foreground": "#c7a0fe"
      }
    },
    {
      "name": "Language methods",
      "scope": [
        "variable.language"
      ],
      "settings": {
        "fontStyle": "italic",
        "foreground": "#ffb6b3"
      }
    },
    {
      "name": "entity.name.method.js",
      "scope": [
        "entity.name.method.js"
      ],
      "settings": {
        "fontStyle": "italic",
        "foreground": "#9d63ee"
      }
    },
    {
      "name": "meta.method.js",
      "scope": [
        "meta.class-method.js entity.name.function.js",
        "variable.function.constructor",
        "keyword.control.conditional.js",
        "keyword.control.conditional.ts",
        "keyword.control.switch.js",
        "keyword.control.switch.ts"
      ],
      "settings": {
        "foreground": "#f36f68"
      }
    },
    {
      "name": "Arrow & assignments",
      "scope": [
        "storage.type.function.arrow.js",
        "storage.type.function.arrow.js.jsx",
        "storage.type.function.arrow.ts",
        "storage.type.function.arrow.tsx",
        "storage.type.function.arrow.coffee",
        "keyword.operator.assignment",
        "keyword.operator.comparison"
      ],
      "settings": {
        "foreground": "#ffb6b3"
      }
    },
    {
      "name": "Function/Class Name - Go",
      "scope": ["entity.name.function.go", "source.go keyword.control.loop.go"],
      "settings": {
        "foreground": "#f3ebff"
      }
    },
    {
      "name": "Function/Class Name - TypeScript",
      "scope": [
        "meta.class.ts entity.name.type.class",
        "meta.class.tsx entity.name.type.class",
        "meta.class meta.function-call variable.function.ts",
        "meta.class meta.function-call variable.function.tsx",
        "source.ts keyword.control.loop.ts",
        "source.tsx keyword.control.loop.tsx",
        "source.ts meta.interface.ts entity.name.type.interface.ts",
        "source.tsx meta.interface.tsx entity.name.type.interface.tsx",
        "source.ts meta.type.declaration.ts entity.name.type.ts",
        "source.tsx meta.type.declaration.tsx entity.name.type.tsx"
      ],
      "settings": {
        "foreground": "#f3ebff"
      }
    },
    {
      "name": "Function/Class Name - Java",
      "scope": [
        "meta.method.identifier.java entity.name.function.java",
        "meta.method.identifier.java storage.type.generic.java",
        "meta.class meta.function-call variable.function.java",
        "source.java keyword.control.loop.java",
        "storage.type.function.arrow.java",
        "meta.class.identifier.java entity.name.type.class.java"
      ],
      "settings": {
        "foreground": "#f3ebff"
      }
    },
    {
      "name": "Function/Class Name - C#",
      "scope": [
        "meta.method.identifier.cs entity.name.function.cs",
        "meta.method.identifier.cs storage.type.generic.cs",
        "meta.class meta.function-call variable.function.cs",
        "source.cs keyword.control.loop.cs",
        "storage.type.function.arrow.cs",
        "meta.class.identifier.cs entity.name.type.class.cs",
        "source.cs entity.name.function.cs",
        "source.cs entity.name.type.class.cs"
      ],
      "settings": {
        "foreground": "#f3ebff"
      }
    },
    {
      "name": "Function/Class Name - Elixir",
      "scope": [
        "source.elixir entity.name.function.elixir",
        "entity.name.type.module.elixir"
      ],
      "settings": {
        "foreground": "#f3ebff"
      }
    },
    {
      "name": "Control Flow - JavaScript",
      "scope": [
        "keyword.control.flow.js",
        "keyword.control.flow.js.jsx",
        "keyword.control.trycatch.js",
        "keyword.control.trycatch.js.jsx",
        "source.js meta.group.braces.curly.js keyword.control.loop.js",
        "source.js.jsx meta.group.braces.curly.js.jsx keyword.control.loop.js.jsx",
        "source.js meta.export.default.js keyword.control.default.js",
        "source.js.jsx meta.export.default.js.jsx keyword.control.default.js.jsx",
        "keyword.control.switch.js",
        "keyword.control.switch.js.jsx"
      ],
      "settings": {
        "foreground": "#ffb6b3"
      }
    },
    {
      "name": "Control Flow - Coffee",
      "scope": [
        "keyword.control.flow.coffee",
        "keyword.control.trycatch.coffee",
        "source.coffee meta.group.braces.curly.coffee keyword.control.loop.coffee",
        "source.coffee meta.export.default.coffee keyword.control.default.coffee",
        "keyword.control.switch.coffee"
      ],
      "settings": {
        "foreground": "#ffb6b3"
      }
    },
    {
      "name": "Control Flow - TypeScript",
      "scope": [
        "keyword.control.flow.ts",
        "keyword.control.flow.tsx",
        "keyword.control.trycatch.ts",
        "keyword.control.trycatch.tsx",
        "source.ts meta.group.braces.curly.ts keyword.control.loop.ts",
        "source.tsx meta.group.braces.curly.tsx keyword.control.loop.tsx",
        "source.ts meta.export.default.ts keyword.control.default.ts",
        "source.tsx meta.export.default.tsx keyword.control.default.tsx",
        "keyword.control.switch.ts",
        "keyword.control.switch.tsx"
      ],
      "settings": {
        "foreground": "#ffb6b3"
      }
    },
    {
      "name": "Control Flow - php",
      "scope": [
        "keyword.control.flow.php",
        "keyword.control.trycatch.php",
        "source.php meta.group.braces.curly.php keyword.control.loop.php",
        "keyword.control.switch.php"
      ],
      "settings": {
        "foreground": "#ffb6b3"
      }
    },
    {
      "name": "Control Flow - Shell Script",
      "scope": [
        "source.shell meta.scope.while-loop.shell keyword.control.shell",
        "source.shell meta.scope.for-in-loop.shell keyword.control.shell"
      ],
      "settings": {
        "foreground": "#ffb6b3",
        "fontStyle": "italic"
      }
    },
    {
      "name": "Control Flow - Shell Script 2",
      "scope": [
        "source.shell meta.scope.while-loop.shell meta.scope.if-block.shell keyword.control.shell",
        "source.shell meta.scope.for-in-loop.shell meta.scope.if-block.shell keyword.control.shell"
      ],
      "settings": {
        "foreground": "#ffb6b3",
        "fontStyle": "italic"
      }
    },
    {
      "name": "Control Flow - Java",
      "scope": [
        "keyword.control.flow.java",
        "keyword.control.trycatch.java",
        "source.java meta.group.braces.curly.java keyword.control.loop.java",
        "keyword.control.switch.java"
      ],
      "settings": {
        "foreground": "#ffb6b3"
      }
    },
    {
      "name": "Control Flow - C#",
      "scope": [
        "source.cs keyword.control.flow",
        "keyword.control.trycatch.cs",
        "source.cs meta.group.braces.curly.cs keyword.control.loop.cs",
        "source.cs keyword.control.switch.cs"
      ],
      "settings": {
        "foreground": "#ffb6b3"
      }
    },
    {
      "name": "Control Flow - Elixir",
      "scope": ["keyword.control.elixir"],
      "settings": {
        "foreground": "#ffb6b3",
        "fontStyle": "italic"
      }
    },
    {
      "name": "Control Flow - Java italic",
      "scope": ["keyword.control.java"],
      "settings": {
        "foreground": "#ffb6b3",
        "fontStyle": "italic"
      }
    },
    {
      "name": "Operator - XML",
      "scope": ["meta.tag.preprocessor.xml"],
      "settings": {
        "foreground": "#ffb6b3"
      }
    },
    {
      "name": "Operator - XML",
      "scope": ["meta.tag.preprocessor.xml entity.other.attribute-name"],
      "settings": {
        "foreground": "#d7cccb"
      }
    },
    {
      "name": "Assignment",
      "scope": "keyword.operator.assignment",
      "settings": {
        "foreground": "#ffb6b3"
      }
    },
    {
      "name": "Logic - JavaScript",
      "scope": [
        "keyword.operator.logical.js",
        "keyword.operator.logical.js.jsx"
      ],
      "settings": {
        "foreground": "#ffb6b3"
      }
    },
    {
      "name": "Logic - Coffee",
      "scope": ["keyword.operator.logical.coffee"],
      "settings": {
        "foreground": "#ffb6b3"
      }
    },
    {
      "name": "Logic - TypeScript",
      "scope": ["keyword.operator.logical.ts", "keyword.operator.logical.tsx"],
      "settings": {
        "foreground": "#ffb6b3"
      }
    },
    {
      "name": "Logic - Go",
      "scope": ["source.go keyword.operator.assignment.go"],
      "settings": {
        "foreground": "#ffb6b3",
        "fontStyle": "normal"
      }
    },
    {
      "name": "Logic - PHP",
      "scope": [
        "source.php keyword.operator",
        "punctuation.separator.inheritance.php"
      ],
      "settings": {
        "foreground": "#ffb6b3"
      }
    },
    {
      "name": "Logic - Shell",
      "scope": ["source.shell meta.scope.logical-expression.shell"],
      "settings": {
        "foreground": "#ffb6b3"
      }
    },
    {
      "name": "Attributes",
      "scope": [
        "entity.other.attribute-name"
      ],
      "settings": {
        "foreground": "#b886fd",
        "fontStyle": "italic"
      }
    },
    {
      "name": "HTML Attributes",
      "scope": [
        "text.html.basic entity.other.attribute-name.html",
        "text.html.basic entity.other.attribute-name"
      ],
      "settings": {
        "foreground": "#d6b9fe"
      }
    },
    {
      "name": "HTML Text Basic",
      "scope": [
        "text.html.basic"
      ],
      "settings": {
        "foreground": "#e4d2fe"
      }
    },
    {
      "name": "CSS Classes and Tags",
      "scope": [
        "entity.other.attribute-name.class"
      ],
      "settings": {
        "foreground": "#f3ebff"
      }
    },
    {
      "name": "CSS ID's",
      "scope": [
        "source.sass keyword.control"
      ],
      "settings": {
        "foreground": "#9d63ee"
      }
    },
    {
      "name": "Inserted",
      "scope": [
        "markup.inserted"
      ],
      "settings": {
        "foreground": "#7a7171"
      }
    },
    {
      "name": "Deleted",
      "scope": [
        "markup.deleted"
      ],
      "settings": {
        "foreground": "#8f51e6",
        "fontStyle": "italic"
      }
    },
    {
      "name": "Diff Deleted",
      "scope": [
        "markup.deleted.diff"
      ],
      "settings": {
        "foreground": "#8f51e6"
      }
    },
    {
      "name": "Diff Inserted",
      "scope": [
        "markup.inserted.diff"
      ],
      "settings": {
        "foreground": "#7a7171",
        "fontStyle": "italic"
      }
    },
    {
      "name": "Changed",
      "scope": [
        "markup.changed"
      ],
      "settings": {
        "foreground": "#b886fd",
        "fontStyle": "italic"
      }
    },
    {
      "name": "Regular Expressions",
      "scope": [
        "string.regexp"
      ],
      "settings": {
        "foreground": "#f87972"
      }
    },
    {
      "name": "Escape Characters",
      "scope": [
        "constant.character.escape"
      ],
      "settings": {
        "foreground": "#f87972"
      }
    },
    {
      "name": "URL",
      "scope": [
        "*url*",
        "*link*",
        "*uri*"
      ],
      "settings": {
        "fontStyle": "underline"
      }
    },
    {
      "name": "Decorators",
      "scope": [
        "tag.decorator.js entity.name.tag.js",
        "tag.decorator.js punctuation.definition.tag.js"
      ],
      "settings": {
        "fontStyle": "italic",
        "foreground": "#8f51e6"
      }
    },
    {
      "name": "ES7 Bind Operator",
      "scope": [
        "source.js constant.other.object.key.js string.unquoted.label.js"
      ],
      "settings": {
        "fontStyle": "italic",
        "foreground": "#8f51e6"
      }
    },
    {
      "name": "JSON Property Names",
      "scope": "support.type.property-name.json",
      "settings": {
        "foreground": "#9d63ee"
      }
    },
    {
      "name": "JSON Support Constants",
      "scope": "support.constant.json",
      "settings": {
        "foreground": "#7a7171"
      }
    },
    {
      "name": "JSON Property values (string)",
      "scope": "meta.structure.dictionary.value.json string.quoted.double",
      "settings": {
        "foreground": "#fc8983"
      }
    },
    {
      "name": "Specific JSON Property values like null",
      "scope":
      "meta.structure.dictionary.json meta.structure.dictionary.value constant.language",
      "settings": {
        "foreground": "#ffb6b3"
      }
    },
    {
      "name": "JSON Key - Level 0",
      "scope": [
        "source.json meta.structure.dictionary.json support.type.property-name.json"
      ],
      "settings": {
        "foreground": "#f3ebff"
      }
    },
    {
      "name": "JSON Key - Level 1",
      "scope": [
        "source.json meta.structure.dictionary.json meta.structure.dictionary.value.json meta.structure.dictionary.json support.type.property-name.json"
      ],
      "settings": {
        "foreground": "#d6b9fe"
      }
    },
    {
      "name": "JSON Key - Level 2",
      "scope": [
        "source.json meta.structure.dictionary.json meta.structure.dictionary.value.json meta.structure.dictionary.json meta.structure.dictionary.value.json meta.structure.dictionary.json support.type.property-name.json"
      ],
      "settings": {
        "foreground": "#c7a0fe"
      }
    },
    {
      "name": "JSON Key - Level 3",
      "scope": [
        "source.json meta.structure.dictionary.json meta.structure.dictionary.value.json meta.structure.dictionary.json meta.structure.dictionary.value.json meta.structure.dictionary.json meta.structure.dictionary.value.json meta.structure.dictionary.json support.type.property-name.json"
      ],
      "settings": {
        "foreground": "#b886fd"
      }
    },
    {
      "name": "JSON Key - Level 4",
      "scope": [
        "source.json meta.structure.dictionary.json meta.structure.dictionary.value.json meta.structure.dictionary.json meta.structure.dictionary.value.json meta.structure.dictionary.json meta.structure.dictionary.value.json meta.structure.dictionary.json meta.structure.dictionary.value.json meta.structure.dictionary.json support.type.property-name.json"
      ],
      "settings": {
        "foreground": "#aa75f5"
      }
    },
    {
      "name": "JSON Key - Level 5",
      "scope": [
        "source.json meta.structure.dictionary.json meta.structure.dictionary.value.json meta.structure.dictionary.json meta.structure.dictionary.value.json meta.structure.dictionary.json meta.structure.dictionary.value.json meta.structure.dictionary.json meta.structure.dictionary.value.json meta.structure.dictionary.json meta.structure.dictionary.value.json meta.structure.dictionary.json support.type.property-name.json"
      ],
      "settings": {
        "foreground": "#9d63ee"
      }
    },
    {
      "name": "JSON Key - Level 6",
      "scope": [
        "source.json meta.structure.dictionary.json meta.structure.dictionary.value.json meta.structure.dictionary.json meta.structure.dictionary.value.json meta.structure.dictionary.json meta.structure.dictionary.value.json meta.structure.dictionary.json meta.structure.dictionary.value.json meta.structure.dictionary.json meta.structure.dictionary.value.json meta.structure.dictionary.json meta.structure.dictionary.value.json meta.structure.dictionary.json support.type.property-name.json"
      ],
      "settings": {
        "foreground": "#8f51e6"
      }
    },
    {
      "name": "JSON Key - Level 7",
      "scope": [
        "source.json meta.structure.dictionary.json meta.structure.dictionary.value.json meta.structure.dictionary.json meta.structure.dictionary.value.json meta.structure.dictionary.json meta.structure.dictionary.value.json meta.structure.dictionary.json meta.structure.dictionary.value.json meta.structure.dictionary.json meta.structure.dictionary.value.json meta.structure.dictionary.json meta.structure.dictionary.value.json meta.structure.dictionary.json meta.structure.dictionary.value.json meta.structure.dictionary.json support.type.property-name.json"
      ],
      "settings": {
        "foreground": "#8f51e6"
      }
    },
    {
      "name": "JSON Key - Level 8",
      "scope": [
        "source.json meta.structure.dictionary.json meta.structure.dictionary.value.json meta.structure.dictionary.json meta.structure.dictionary.value.json meta.structure.dictionary.json meta.structure.dictionary.value.json meta.structure.dictionary.json meta.structure.dictionary.value.json meta.structure.dictionary.json meta.structure.dictionary.value.json meta.structure.dictionary.json meta.structure.dictionary.value.json meta.structure.dictionary.json meta.structure.dictionary.value.json meta.structure.dictionary.json meta.structure.dictionary.value.json meta.structure.dictionary.json support.type.property-name.json"
      ],
      "settings": {
        "foreground": "#8f51e6"
      }
    },
    {
      "name": "Markdown - Plain",
      "scope": [
        "text.html.markdown",
        "punctuation.definition.list_item.markdown"
      ],
      "settings": {
        "foreground": "#f3ebff"
      }
    },
    {
      "name": "Markdown - Plain",
      "scope": [
        "beginning.punctuation.definition.list.markdown"
      ],
      "settings": {
        "foreground": "#ffb6b3"
      }
    },
    {
      "name": "Markdown - Markup Raw Inline",
      "scope": [
        "text.html.markdown markup.inline.raw.markdown"
      ],
      "settings": {
        "foreground": "#b886fd"
      }
    },
    {
      "name": "Markdown - Markup Raw Inline Punctuation",
      "scope": [
        "text.html.markdown markup.inline.raw.markdown punctuation.definition.raw.markdown"
      ],
      "settings": {
        "foreground": "#9a90a7"
      }
    },
    {
      "name": "Markdown - Line Break",
      "scope": [
        "text.html.markdown meta.dummy.line-break"
      ],
      "settings": {
        "foreground": ""
      }
    },
    {
      "name": "Markdown - Heading",
      "scope": [
        "markdown.heading",
        "markup.heading | markup.heading entity.name",
        "markup.heading.markdown punctuation.definition.heading.markdown",
        "markup.heading1",
        "markup.heading.markdown",
        "entity.name",
        "entity.name.section.markdown",
        "heading.1.markdown"
      ],
      "settings": {
        "foreground": "#ffb6b3"
      }
    },
    {
      "name": "Markdown - Heading Punctuation",
      "scope": [
        "markup.heading.markdown punctuation.definition.heading.markdown"
      ],
      "settings": {
        "foreground": "#e4d2fe"
      }
    },
    {
      "name": "Markup - Italic",
      "scope": [
        "markup.italic.markdown"
      ],
      "settings": {
        "fontStyle": "italic"
      }
    },
    {
      "name": "Markup - Bold",
      "scope": [
        "markup.bold",
        "markup.bold string"
      ],
      "settings": {
        "fontStyle": "bold",
        "foreground": "#8d8281"
      }
    },
    {
      "name": "Markup - Bold-Italic",
      "scope": [
        "markup.bold markup.italic",
        "markup.italic markup.bold",
        "markup.quote markup.bold",
        "markup.bold markup.italic string",
        "markup.italic markup.bold string",
        "markup.quote markup.bold string"
      ],
      "settings": {
        "fontStyle": "bold",
        "foreground": "#8d8281"
      }
    },
    {
      "name": "Markup - Underline",
      "scope": [
        "markup.underline"
      ],
      "settings": {
        "fontStyle": "underline",
        "foreground": "#e4d2fe"
      }
    },
    {
      "name": "Markup - Strike",
      "scope": [
        "markup.strike"
      ],
      "settings": {
        "fontStyle": "strike",
        "foreground": ""
      }
    },
    {
      "name": "Markdown - Blockquote",
      "scope": [
        "markup.quote punctuation.definition.blockquote.markdown"

      ],
      "settings": {
        "background": "#9a90a7",
        "foreground": "#2a2433"
      }
    },
    {
      "name": "Markdown - Blockquote",
      "scope": [
        "markup.quote.markdown"

      ],
      "settings": {
        "foreground": "#e4d2fe",
        "fontStyle": "italic"
      }
    },
    {
      "name": "Markdown - > Blockquote",
      "scope": [
        "beginning.punctuation.definition.quote.markdown"

      ],
      "settings": {
        "foreground": "#cf504a"
      }
    },
    {
      "name": "Markdown - ! Img",
      "scope": [
        "meta.paragraph.markdown"

      ],
      "settings": {
        "foreground": "#e4d2fe"
      }
    },
    {
      "name": "Markdown - **Bold** _Italic_",
      "scope": [
        "punctuation.definition.bold.markdown",
        "punctuation.definition.italic.markdown"

      ],
      "settings": {
        "foreground": "#d6b9fe"
      }
    },
    {
      "name": "Markup - Quote",
      "scope": [
        "markup.quote"
      ],
      "settings": {
        "fontStyle": "italic",
        "foreground": ""
      }
    },
    {
      "name": "Markdown - Link",
      "scope": [
        "string.other.link.title.markdown"
      ],
      "settings": {
        "foreground": "#ffb6b3"
      }
    },
    {
      "name": "Markdown - Link",
      "scope": [
        "markup.underline.link.markdown"
      ],
      "settings": {
        "foreground": "#d6b9fe"
      }
    },
    {
      "name": "Markdown - Link Description",
      "scope": [
        "string.other.link.description.title.markdown"
      ],
      "settings": {
        "foreground": "#b886fd"
      }
    },
    {
      "name": "Markdown - Link Anchor",
      "scope": [
        "constant.other.reference.link.markdown"
      ],
      "settings": {
        "foreground": "#9f9393"
      }
    },
    {
      "name": "Markup - Raw Block",
      "scope": [
        "markup.raw.block"
      ],
      "settings": {
        "foreground": "#b886fd"
      }
    },
    {
      "name": "Markdown - Raw Block Fenced",
      "scope": [
        "markup.raw.block.fenced.markdown"
      ],
      "settings": {
        "foreground": "#2a243350"
      }
    },
    {
      "name": "Markdown - Fenced Bode Block",
      "scope": [
        "punctuation.definition.fenced.markdown"
      ],
      "settings": {
        "foreground": "#2a243350"
      }
    },
    {
      "name": "Markdown - Fenced Bode Block Variable",
      "scope": [
        "markup.raw.block.fenced.markdown",
        "variable.language.fenced.markdown",
        "punctuation.section.class.end"
      ],
      "settings": {
        "foreground": "#f3ebff"
      }
    },
    {
      "name": "Markdown - Fenced Language",
      "scope": [
        "variable.language.fenced.markdown"
      ],
      "settings": {
        "foreground": "#9a90a7"
      }
    },
    {
      "name": "Markdown - Separator",
      "scope": [
        "meta.separator"
      ],
      "settings": {
        "fontStyle": "bold",
        "background": "#2a2433",
        "foreground": "#9a90a7"
      }
    },
    {
      "name": "Markup - Table",
      "scope": [
        "markup.table"
      ],
      "settings": {
        "foreground": "#f3ebff"
      }
    },
    {
      "scope": "token.info-token",
      "settings": {
        "foreground": "#aa75f5"
      }
    },
    {
      "scope": "token.warn-token",
      "settings": {
        "foreground": "#8d8281"
      }
    },
    {
      "scope": "token.error-token",
      "settings": {
        "foreground": "#8f51e6"
      }
    },
    {
      "scope": "token.debug-token",
      "settings": {
        "foreground": "#b886fd"
      }
    },
    {
      "name": "String",
      "scope": [
        "string",
        "string.quoted"
      ],
      "settings": {
        "foreground": "#ffb6b3"
      }
    },
    {
      "name": "Variable Other",
      "scope": [
        "meta.attribute-selector.css entity.other.attribute-name.attribute",
        "variable.other.readwrite.js"
      ],
      "settings": {
        "foreground": "#d6b9fe"
      }
    },
    {
      "name": "Support Constant Math",
      "scope": "support.constant.math",
      "settings": {
        "foreground": "#7a7171"
      }
    },
    {
      "name": "Regexp",
      "scope": "string.regexp",
      "settings": {
        "foreground": "#7a7171"
      }
    },
    {
      "name": "Number",
      "scope": ["constant.numeric", "constant.character.numeric"],
      "settings": {
        "foreground": "#ff9e99"
      }
    },
    {
      "name": "Variable",
      "scope": [
        "variable.language",
        "variable.other"
      ],
      "settings": {
        "foreground": "#ffb6b3"
      }
    },
    {
      "name": "Variable",
      "scope": [
        "variable.language.this.js",
        "variable.language.this.php"
      ],
      "settings": {
        "foreground": "#ffb6b3",
        "fontStyle": "italic"
      }
    },
    {
      "name": "Keyword",
      "scope": "keyword",
      "settings": {
        "foreground": "#7a7171"
      }
    },
    {
      "name": "Storage",
      "scope": [
        "storage",
        "meta.var.expr",
        "meta.class meta.method.declaration meta.var.expr storage.type.js",
        "storage.type.property.js",
        "storage.type.property.ts",
        "storage.type.property.tsx"
      ],
      "settings": {
        "foreground": "#ff9e99",
        "fontStyle": "italic"
      }
    },
    {
      "name": "Storage Type Class",
      "scope": [
        "storage.type.class.js"
      ],
      "settings": {
        "foreground": "#ffb6b3"
      }
    },
    {
      "name": "Class name",
      "scope": ["entity.name.class", "meta.class entity.name.type.class"],
      "settings": {
        "foreground": "#e4d2fe"
      }
    },
    {
      "name": "Class name type",
      "scope": [
        "entity.name.type"
      ],
      "settings": {
        "fontStyle": "",
        "foreground": "#afa7b9"
      }
    },
    {
      "name": "Function name",
      "scope": "entity.name.function",
      "settings": {
        "foreground": "#c7a0fe"
      }
    },
    {
      "name": "Variable start",
      "scope": "punctuation.definition.variable",
      "settings": {
        "foreground": "#afa7b9"
      }
    },
    {
      "name": "Embedded code markers",
      "scope": [
        "punctuation.section.embedded.begin",
        "punctuation.section.embedded.end"
      ],
      "settings": {
        "foreground": "#635775"
      }
    },
    {
      "name": "Built-in constant",
      "scope": [
        "constant.language",
        "punctuation.definition.constant",
        "variable.other.constant",
        "meta.preprocessor"
      ],
      "settings": {
        "foreground": "#f3ebff"
      }
    },
    {
      "name": "Support.construct",
      "scope": [
        "support.function.construct",
        "keyword.other.new"
      ],
      "settings": {
        "foreground": "#d95f59"
      }
    },
    {
      "name": "User-defined constant",
      "scope": [
        "constant.character",
        "constant.other"
      ],
      "settings": {
        "foreground": "#ffb6b3"
      }
    },
    {
      "name": "Constant Character Escape",
      "scope": "constant.character.escape",
      "settings": {
        "foreground": "#8d8281"
      }
    },
    {
      "name": "RegExp String",
      "scope": ["string.regexp", "string.regexp keyword.other"],
      "settings": {
        "foreground": "#9a90a7"
      }
    },
    {
      "name": "Inherited class",
      "scope": "entity.other.inherited-class",
      "settings": {
        "foreground": "#e4d2fe"
      }
    },
    {
      "name": "Tag name",
      "scope": "entity.name.tag",
      "settings": {
        "foreground": "#f3ebff"
      }
    },
    {
      "name": "Tag start/end Meta",
      "scope": ["punctuation.definition.tag", "meta.tag"],
      "settings": {
        "foreground": "#857897"
      }
    },
    {
      "name": "HTML Tag names",
      "scope": [
        "entity.name.tag",
        "meta.tag.other.html",
        "meta.tag.other.js",
        "meta.tag.other.tsx",
        "entity.name.tag.tsx",
        "entity.name.tag.js",
        "entity.name.tag",
        "meta.tag.js",
        "meta.tag.tsx",
        "meta.tag.html"
      ],
      "settings": {
        "foreground": "#f3ebff"
      }
    },
    {
      "name": "Tag attribute",
      "scope": "entity.other.attribute-name",
      "settings": {
        "foreground": "#f3ebff",
        "fontStyle": "italic"
      }
    },
    {
      "name": "Entity Name Tag Custom",
      "scope": "entity.name.tag.custom",
      "settings": {
        "foreground": "#aa75f5"
      }
    },
    {
      "name": "Library function",
      "scope": "support.function",
      "settings": {
        "foreground": "#d6b9fe"
      }
    },
    {
      "name": "Continuation",
      "scope": "punctuation.separator.continuation",
      "settings": {
        "foreground": "#8f51e6"
      }
    },
    {
      "name": "Invalid Broken",
      "scope": "invalid.broken",
      "settings": {
        "foreground": "#1e1b22",
        "background": "#8d8281"
      }
    },
    {
      "name": "Invalid Unimplemented",
      "scope": "invalid.unimplemented",
      "settings": {
        "background": "#7a7171",
        "foreground": "#f3ebff"
      }
    },
    {
      "name": "Invalid Illegal",
      "scope": "invalid.illegal",
      "settings": {
        "background": "#8f51e6",
        "foreground": "#f3ebff"
      }
    },
    {
      "name": "Library class/type",
      "scope": [
        "support.type",
        "support.class"
      ],
      "settings": {
        "foreground": "#f87972"
      }
    },
    {
      "name": "Support Variable DOM",
      "scope": "support.variable.dom",
      "settings": {
        "foreground": "#ffb6b3"
      }
    },
    {
      "name": "Library Exception",
      "scope": "support.type.exception",
      "settings": {
        "foreground": "#8d8281"
      }
    },
    {
      "name": "Library variable",
      "scope": "support.other.variable",
      "settings": {}
    },
    {
      "name": "Invalid",
      "scope": "invalid",
      "settings": {
        "background": "#8f51e6",
        "foreground": "#f3ebff"
      }
    },
    {
      "name": "Invalid deprecated",
      "scope": "invalid.deprecated",
      "settings": {
        "background": "#9f9393",
        "foreground": "#8d8281"
      }
    },
    {
      "name": "Keyword Operator",
      "scope": "keyword.operator",
      "settings": {
        "foreground": "#f87972",
        "fontStyle": "normal"
      }
    },
    {
      "name": "Keyword Operator Relational",
      "scope": "keyword.operator.relational",
      "settings": {
        "foreground": "#b886fd",
        "fontStyle": "italic"
      }
    },
    {
      "name": "Keyword Operator Assignment",
      "scope": "keyword.operator.assignment",
      "settings": {
        "foreground": "#ffb6b3"
      }
    },
    {
      "name": "Keyword Operator Arithmetic",
      "scope": "keyword.operator.arithmetic",
      "settings": {
        "foreground": "#c7a0fe"
      }
    },
    {
      "name": "Keyword Operator Bitwise",
      "scope": "keyword.operator.bitwise",
      "settings": {
        "foreground": "#b886fd"
      }
    },
    {
      "name": "Keyword Operator Increment",
      "scope": "keyword.operator.increment",
      "settings": {
        "foreground": "#b886fd"
      }
    },
    {
      "name": "Keyword Operator Ternary",
      "scope": "keyword.operator.ternary",
      "settings": {
        "foreground": "#b886fd"
      }
    },
    {
      "name": "Double-Slashed Comment",
      "scope": "comment.line.double-slash",
      "settings": {
        "foreground": "#706383"
      }
    },
    {
      "name": "Object",
      "scope": "object",
      "settings": {
        "foreground": "#aa75f5"
      }
    },
    {
      "name": "Null",
      "scope": "constant.language.null",
      "settings": {
        "foreground": "#f3ebff"
      }
    },
    {
      "name": "Meta Brace",
      "scope": "meta.brace",
      "settings": {
        "foreground": "#706383"
      }
    },
    {
      "name": "Meta Delimiter Period",
      "scope": "meta.delimiter.period",
      "settings": {
        "foreground": "#e4d2fe",
        "fontStyle": "italic"
      }
    },
    {
      "name": "Boolean",
      "scope": "constant.language.boolean",
      "settings": {
        "foreground": "#f36f68"
      }
    },
    {
      "name": "Object Comma",
      "scope": "object.comma",
      "settings": {
        "foreground": "#f3ebff"
      }
    },
    {
      "name": "Variable Parameter Function",
      "scope": "variable.parameter.function",
      "settings": {
        "foreground": "#f87972"
      }
    },
    {
      "name": "Support Type Property Name & entity name tags",
      "scope": [
        "support.type.vendor.property-name",
        "support.constant.vendor.property-value",
        "support.type.property-name",
        "meta.property-list entity.name.tag"
      ],
      "settings": {
        "foreground": "#9f9393"
      }
    },
    {
      "name": "Entity Name tag reference in stylesheets",
      "scope": "meta.property-list entity.name.tag.reference",
      "settings": {
        "foreground": "#aa75f5"
      }
    },
    {
      "name": "Constant Other Color RGB Value Punctuation Definition Constant",
      "scope": "constant.other.color.rgb-value punctuation.definition.constant",
      "settings": {
        "foreground": "#8d8281"
      }
    },
    {
      "name": "Meta Selector",
      "scope": "meta.selector",
      "settings": {
        "foreground": "#b886fd",
        "fontStyle": "italic"
      }
    },
    {
      "name": "Entity Other Attribute Name Id",
      "scope": "entity.other.attribute-name.id",
      "settings": {
        "foreground": "#fc8983"
      }
    },
    {
      "name": "Meta Property Name",
      "scope": "meta.property-name",
      "settings": {
        "foreground": "#f87972"
      }
    },
    {
      "name": "Doctypes",
      "scope": ["entity.name.tag.doctype", "meta.tag.sgml.doctype"],
      "settings": {
        "foreground": "#706383",
        "fontStyle": "italic"
      }
    },
    {
      "name": "Keyword Control Operator",
      "scope": "keyword.control.operator",
      "settings": {
        "foreground": "#f87972"
      }
    },
    {
      "name": "Keyword Operator Logical",
      "scope": "keyword.operator.logical",
      "settings": {
        "foreground": "#b886fd"
      }
    },
    {
      "name": "Variable Instances",
      "scope": [
        "variable.instance",
        "variable.other.instance",
        "variable.readwrite.instance",
        "variable.other.readwrite.instance",
        "variable.other.property"
      ],
      "settings": {
        "foreground": "#d6b9fe"
      }
    },
    {
      "name": "Variable Property Other object property",
      "scope": ["variable.other.object.property"],
      "settings": {
        "foreground": "#e4d2fe",
        "fontStyle": "italic"
      }
    },
    {
      "name": "Function call JSX",
      "scope": "meta.function-call.js.jsx entity.name.function.js.jsx",
      "settings": {
        "foreground": "#b886fd"
      }
    },
    {
      "name": "Variable Property Other object",
      "scope": [
        "variable.other.object.js",
        "variable.other.object.jsx",
        "variable.object.property.js",
        "variable.object.property.jsx"
      ],
      "settings": {
        "foreground": "#e4d2fe"
      }
    },
    {
      "name":
      "Keyword Operator Comparison, imports, returns and Keyword Operator Ruby",
      "scope": [
        "keyword.operator.comparison",
        "keyword.control.flow.js",
        "keyword.control.flow.ts",
        "keyword.control.flow.tsx",
        "keyword.control.ruby",
        "keyword.control.module.ruby",
        "keyword.control.class.ruby",
        "keyword.control.def.ruby",
        "keyword.control.loop.js",
        "keyword.control.loop.ts",
        "keyword.control.import.js",
        "keyword.control.import.ts",
        "keyword.control.import.tsx",
        "keyword.control.from.js",
        "keyword.control.from.ts",
        "keyword.control.from.tsx"
      ],
      "settings": {
        "foreground": "#ffb6b3",
        "fontStyle": "italic"
      }
    },
    {
      "name": "Variable Interpolation",
      "scope": "variable.interpolation",
      "settings": {
        "foreground": "#8f51e6"
      }
    },
    {
      "name": "Support Variable Property",
      "scope": "support.variable.property",
      "settings": {
        "foreground": "#f87972"
      }
    },
    {
      "name": "Template Strings",
      "scope": "string.template meta.template.expression",
      "settings": {
        "foreground": "#8f51e6"
      }
    },
    {
      "name": "Backtics(``) in Template Strings",
      "scope": "string.template punctuation.definition.string",
      "settings": {
        "foreground": "#e4d2fe"
      }
    },
    {
      "name": "Italics",
      "scope": "italic",
      "settings": {
        "foreground": "#b886fd",
        "fontStyle": "italic"
      }
    },
    {
      "name": "Bold",
      "scope": "bold",
      "settings": {
        "foreground": "#7a7171",
        "fontStyle": "bold"
      }
    },
    {
      "name": "Quote",
      "scope": "quote",
      "settings": {
        "foreground": "#706383",
        "fontStyle": "italic"
      }
    },
    {
      "name": "Raw Code",
      "scope": "raw",
      "settings": {
        "foreground": "#afa7b9"
      }
    },
    {
      "name": "CoffeScript Variable Assignment",
      "scope": "variable.assignment.coffee",
      "settings": {
        "foreground": "#f87972"
      }
    },
    {
      "name": "CoffeScript Parameter Function",
      "scope": "variable.parameter.function.coffee",
      "settings": {
        "foreground": "#e4d2fe"
      }
    },
    {
      "name": "CoffeeScript Assignments",
      "scope": "variable.assignment.coffee",
      "settings": {
        "foreground": "#7a7171"
      }
    },
    {
      "name": "C# Readwrite Variables",
      "scope": "variable.other.readwrite.cs",
      "settings": {
        "foreground": "#e4d2fe"
      }
    },
    {
      "name": "C# Classes & Storage types",
      "scope": ["entity.name.type.class.cs", "storage.type.cs"],
      "settings": {
        "foreground": "#9d63ee"
      }
    },
    {
      "name": "C# Namespaces",
      "scope": "entity.name.type.namespace.cs",
      "settings": {
        "foreground": "#afa7b9"
      }
    },
    {
      "name": "Tag names in Stylesheets",
      "scope": [
        "entity.name.tag.css",
        "entity.name.tag.less",
        "entity.name.tag.custom.css",
        "support.constant.property-value.css"
      ],
      "settings": {
        "foreground": "#f3ebff"
      }
    },
    {
      "name": "Wildcard(*) selector in Stylesheets",
      "scope": [
        "entity.name.tag.wildcard.css",
        "entity.name.tag.wildcard.less",
        "entity.name.tag.wildcard.scss",
        "entity.name.tag.wildcard.sass"
      ],
      "settings": {
        "foreground": "#f3ebff"
      }
    },
    {
      "name": "CSS Keyword Other Unit",
      "scope": [
        "keyword.other.unit.css",
        "keyword.other.unit.px.css",
        "keyword.other.unit.vw.css",
        "keyword.other.unit.vh.css",
        "keyword.other.unit.ch.css",
        "keyword.other.unit.ex.css",
        "keyword.other.unit.percentage.css",
        "keyword.other.unit.rem.css",
        "keyword.other.unit.em.css"
      ],
      "settings": {
        "foreground": "#ed655e"
      }
    },
    {
      "name": "CSS Keyword @Rule",
      "scope": [
        "keyword.control.at-rule.media.css"
      ],
      "settings": {
        "foreground": "#ff9e99"
      }
    },
    {
      "name": "CSS class and ID",
      "scope": [
        "entity.other.attribute-name.id",
        "punctuation.definition.entity.css"
      ],
      "settings": {
        "foreground": "#ffb6b3"
      }
    },
    {
      "name": "Elixir Classes",
      "scope": [
        "source.elixir support.type.elixir",
        "source.elixir meta.module.elixir entity.name.class.elixir"
      ],
      "settings": {
        "foreground": "#9d63ee"
      }
    },
    {
      "name": "Elixir Functions",
      "scope": "source.elixir entity.name.function",
      "settings": {
        "foreground": "#7a7171"
      }
    },
    {
      "name": "Elixir Constants",
      "scope": [
        "source.elixir constant.other.symbol.elixir",
        "source.elixir constant.other.keywords.elixir"
      ],
      "settings": {
        "foreground": "#aa75f5"
      }
    },
    {
      "name": "Elixir",
      "scope": [
        "source.elixir variable.other.readwrite.module.elixir",
        "source.elixir variable.other.readwrite.module.elixir punctuation.definition.variable.elixir"
      ],
      "settings": {
        "foreground": "#7a7171"
      }
    },
    {
      "name": "Elixir Binary Punctuations",
      "scope": "source.elixir .punctuation.binary.elixir",
      "settings": {
        "foreground": "#b886fd",
        "fontStyle": "italic"
      }
    },
    {
      "name": "Go Function Calls",
      "scope": "source.go meta.function-call.go",
      "settings": {
        "foreground": "#afa7b9"
      }
    },
    {
      "name": "Go Keywords",
      "scope": [
        "source.go keyword.package.go",
        "source.go keyword.import.go",
        "source.go keyword.function.go",
        "source.go keyword.type.go",
        "source.go keyword.struct.go",
        "source.go keyword.interface.go",
        "source.go keyword.const.go",
        "source.go keyword.var.go",
        "source.go keyword.map.go",
        "source.go keyword.channel.go",
        "source.go keyword.control.go"
      ],
      "settings": {
        "foreground": "#b886fd",
        "fontStyle": "italic"
      }
    },
    {
      "name": "Go Constants e.g. nil, string format (%s, %d, etc.)",
      "scope": [
        "source.go constant.language.go",
        "source.go constant.other.placeholder.go"
      ],
      "settings": {
        "foreground": "#8f51e6"
      }
    },
    {
      "name": "JavaScript Classes",
      "scope": [
        "meta.class entity.name.type.class",
        "entity.global.clojure"
      ],
      "settings": {
        "foreground": "#f3ebff"
      }
    },
    {
      "name": "JavaScript Method Declaration e.g. `constructor`",
      "scope": [
        "meta.method.declaration storage.type.js",
        "meta.symbol.clojure"
      ],
      "settings": {
        "foreground": "#d6b9fe"
      }
    },
    {
      "name": "JavaScript Terminator",
      "scope": "terminator.js",
      "settings": {
        "foreground": "#e4d2fe"
      }
    },
    {
      "name": "JavaScript Meta Punctuation Definition",
      "scope": "meta.js punctuation.definition.js",
      "settings": {
        "foreground": "#e4d2fe"
      }
    },
    {
      "name": "Entity Names in Code Documentations",
      "scope": [
        "entity.name.type.instance.jsdoc",
        "entity.name.type.instance.phpdoc"
      ],
      "settings": {
        "foreground": "#706383"
      }
    },
    {
      "name": "Other Variables in Code Documentations",
      "scope": ["variable.other.jsdoc", "variable.other.phpdoc"],
      "settings": {
        "foreground": "#f87972"
      }
    },
    {
      "name": "JavaScript module imports and exports",
      "scope": [
        "variable.other.meta.import.js",
        "meta.import.js variable.other",
        "variable.other.meta.export.js",
        "meta.export.js variable.other"
      ],
      "settings": {
        "foreground": "#e4d2fe"
      }
    },
    {
      "name": "JavaScript Variable Parameter Function",
      "scope": "variable.parameter.function.js",
      "settings": {
        "foreground": "#9d63ee"
      }
    },
    {
      "name": "JavaScript Variables",
      "scope": ["variable.js", "variable.other.js"],
      "settings": {
        "foreground": "#e4d2fe"
      }
    },
    {
      "name": "JavaScript Entity Name Type",
      "scope": ["entity.name.type.js", "entity.name.type.module.js"],
      "settings": {
        "foreground": "#f36f68"
      }
    },
    {
      "name": "JavaScript Support Classes",
      "scope": "support.class.js",
      "settings": {
        "foreground": "#e4d2fe"
      }
    },
    {
      "name": "Ruby Variables",
      "scope": ["variable.other.ruby"],
      "settings": {
        "foreground": "#e4d2fe"
      }
    },
    {
      "name": "Ruby Class",
      "scope": ["entity.name.type.class.ruby"],
      "settings": {
        "foreground": "#c7a0fe"
      }
    },
    {
      "name": "Ruby Hashkeys",
      "scope": "constant.language.symbol.hashkey.ruby",
      "settings": {
        "foreground": "#9d63ee"
      }
    },
    {
      "name": "Attribute Name for LESS",
      "scope":
      "meta.attribute-selector.less entity.other.attribute-name.attribute",
      "settings": {
        "foreground": "#aa75f5"
      }
    },
    {
      "name": "PHP Variables",
      "scope": ["variable.other.php", "variable.other.property.php"],
      "settings": {
        "foreground": "#e4d2fe"
      }
    },
    {
      "name": "Support Classes in PHP",
      "scope": "support.class.php",
      "settings": {
        "foreground": "#c7a0fe"
      }
    },
    {
      "name": "Punctuations in PHP function calls",
      "scope": "meta.function-call.php punctuation",
      "settings": {
        "foreground": "#e4d2fe"
      }
    },
    {
      "name": "PHP Global Variables",
      "scope": "variable.other.global.php",
      "settings": {
        "foreground": "#b886fd"
      }
    },
    {
      "name": "Declaration Punctuation in PHP Global Variables",
      "scope": "variable.other.global.php punctuation.definition.variable",
      "settings": {
        "foreground": "#b886fd"
      }
    },
    {
      "name": "Language Constants in Python",
      "scope": "constant.language.python",
      "settings": {
        "foreground": "#b886fd"
      }
    },
    {
      "name": "Python Function Parameter and Arguments",
      "scope": [
        "variable.parameter.function.python",
        "meta.function-call.arguments.python"
      ],
      "settings": {
        "foreground": "#9d63ee"
      }
    },
    {
      "name": "Python Function Call",
      "scope": [
        "meta.function-call.python",
        "meta.function-call.generic.python"
      ],
      "settings": {
        "foreground": "#e4d2fe"
      }
    },
    {
      "name": "Punctuations in Python",
      "scope": "punctuation.python",
      "settings": {
        "foreground": "#e4d2fe"
      }
    },
    {
      "name": "Decorator Functions in Python",
      "scope": "entity.name.function.decorator.python",
      "settings": {
        "foreground": "#8f51e6"
      }
    },
    {
      "name": "Python Language Variable",
      "scope": "source.python variable.language.special",
      "settings": {
        "foreground": "#9d63ee"
      }
    },
    {
      "name": "SCSS Variable",
      "scope": [
        "variable.scss",
        "variable.sass",
        "variable.parameter.url.scss",
        "variable.parameter.url.sass"
      ],
      "settings": {
        "foreground": "#d6b9fe"
      }
    },
    {
      "name": "Variables in SASS At-Rules",
      "scope": [
        "source.css.scss meta.at-rule variable",
        "source.css.sass meta.at-rule variable"
      ],
      "settings": {
        "foreground": "#f3ebff"
      }
    },
    {
      "name": "Attribute Name for SASS",
      "scope": [
        "meta.attribute-selector.scss entity.other.attribute-name.attribute",
        "meta.attribute-selector.sass entity.other.attribute-name.attribute"
      ],
      "settings": {
        "foreground": "#9d63ee"
      }
    },
    {
      "name": "Tag names in SASS",
      "scope": ["entity.name.tag.scss", "entity.name.tag.sass"],
      "settings": {
        "foreground": "#f3ebff"
      }
    },
    {
      "name": "SASS Keyword Other Unit",
      "scope": ["keyword.other.unit.scss", "keyword.other.unit.sass"],
      "settings": {
        "foreground": "#d95f59"
      }
    },
    {
      "name": "TypeScript[React] Variables and Object Properties",
      "scope": [
        "variable.other.readwrite.alias.ts",
        "variable.other.readwrite.alias.tsx",
        "variable.other.readwrite.ts",
        "variable.other.readwrite.tsx",
        "variable.other.object.ts",
        "variable.other.object.tsx",
        "variable.object.property.ts",
        "variable.object.property.tsx",
        "variable.other.ts",
        "variable.other.tsx",
        "variable.tsx",
        "variable.ts"
      ],
      "settings": {
        "foreground": "#e4d2fe"
      }
    },
    {
      "name": "TypeScript[React] Entity Name Types",
      "scope": ["entity.name.type.ts", "entity.name.type.tsx"],
      "settings": {
        "foreground": "#9d63ee"
      }
    },
    {
      "name": "TypeScript[React] Node Classes",
      "scope": ["support.class.node.ts", "support.class.node.tsx"],
      "settings": {
        "foreground": "#9d63ee"
      }
    },
    {
      "name": "TypeScript[React] Entity Name Types as Parameters",
      "scope": [
        "meta.type.parameters.ts entity.name.type",
        "meta.type.parameters.tsx entity.name.type"
      ],
      "settings": {
        "foreground": "#706383"
      }
    },
    {
      "name": "TypeScript[React] Import/Export Punctuations",
      "scope": [
        "meta.import.ts punctuation.definition.block",
        "meta.import.tsx punctuation.definition.block",
        "meta.export.ts punctuation.definition.block",
        "meta.export.tsx punctuation.definition.block"
      ],
      "settings": {
        "foreground": "#e4d2fe"
      }
    },
    {
      "name": "TypeScript[React] Punctuation Decorators",
      "scope": [
        "meta.decorator punctuation.decorator.ts",
        "meta.decorator punctuation.decorator.tsx"
      ],
      "settings": {
        "foreground": "#9d63ee"
      }
    },
    {
      "name": "TypeScript[React] Punctuation Decorators",
      "scope": "meta.tag.js meta.jsx.children.tsx",
      "settings": {
        "foreground": "#9d63ee"
      }
    },
    {
      "name": "YAML Entity Name Tags",
      "scope": "entity.name.tag.yaml",
      "settings": {
        "foreground": "#e4d2fe"
      }
    },
    {
      "name": "JavaScript Variable Other ReadWrite",
      "scope": ["variable.other.readwrite.js", "variable.parameter"],
      "settings": {
        "foreground": "#e4d2fe"
      }
    },
    {
      "name": "Support Class Component",
      "scope": ["support.class.component.js", "support.class.component.tsx"],
      "settings": {
        "foreground": "#f3ebff"
      }
    },
    {
      "name": "Text nested in React tags",
      "scope": [
        "meta.jsx.children",
        "meta.jsx.children.js",
        "meta.jsx.children.tsx"
      ],
      "settings": {
        "foreground": "#e4d2fe"
      }
    },
    {
      "name": "TypeScript Entity Name Type",
      "scope": ["entity.name.type.tsx", "entity.name.type.module.tsx"],
      "settings": {
        "foreground": "#f36f68"
      }
    },
    {
      "name": "TypeScript Method Declaration e.g. `constructor`",
      "scope": [
        "meta.method.declaration storage.type.ts",
        "meta.method.declaration storage.type.tsx"
      ],
      "settings": {
        "foreground": "#d6b9fe"
      }
    },
    {
      "name": "diff: header",
      "scope": [
        "meta.diff",
        "meta.diff.header"
      ],
      "settings": {
        "background": "#1e1b22",
        "fontStyle": "italic",
        "foreground": "#e4d2fe"
      }
    },
    {
      "name": "diff: deleted",
      "scope": "markup.deleted",
      "settings": {
        "background": "#8f51e6",
        "foreground": "#e4d2fe"
      }
    },
    {
      "name": "diff: changed",
      "scope": "markup.changed",
      "settings": {
        "background": "#aa75f5",
        "foreground": "#e4d2fe"
      }
    },
    {
      "name": "diff: inserted",
      "scope": "markup.inserted",
      "settings": {
        "background": "#8f51e6",
        "foreground": "#e4d2fe"
      }
    },
    {
      "name": "Markup Quote",
      "scope": "markup.quote",
      "settings": {
        "foreground": "#8f51e6",
        "fontStyle": "italic"
      }
    },
    {
      "name": "Markup Lists",
      "scope": "markup.list",
      "settings": {
        "foreground": "#e4d2fe"
      }
    },
    {
      "name": "Markup Styling",
      "scope": [
        "markup.bold",
        "markup.italic"
      ],
      "settings": {
        "foreground": "#e4d2fe"
      }
    },
    {
      "name": "Markup Inline",
      "scope": "markup.inline.raw",
      "settings": {
        "fontStyle": "",
        "foreground": "#ffb6b3"
      }
    },
    {
      "name": "Markup Setext Header",
      "scope": "markup.heading.setext",
      "settings": {
        "fontStyle": "",
        "foreground": "#aa75f5"
      }
    }
  ],
  "colors": {
    "focusBorder": "#574b6880",
    "foreground": "#afa7b9",
    "widget.shadow": "#1e1b22",
    "selection.background": "#aa75f5",
    "descriptionForeground": "#e4d2fe",
    "textLink.foreground": "#f87972",
    "textLink.activeForeground": "#f87972",
    "input.background": "#372f42",
    "input.foreground": "#e4d2fe",
    "input.border": "#574b68",
    "input.placeholderForeground": "#afa7b9",
    "inputOption.activeBorder": "#f87972",
    "inputValidation.infoBorder": "#9d63ee",
    "inputValidation.infoBackground": "#2a2433",
    "inputValidation.warningBackground": "#aa75f5",
    "inputValidation.warningBorder": "#aa75f5",
    "inputValidation.errorBackground": "#8f51e6",
    "inputValidation.errorBorder": "#8f51e6",
    "punctuation.definition.generic.begin.html":  "#b886fd",
    "errorForeground": "#8f51e6",
    "badge.background": "#8f51e6",
    "badge.foreground": "#f3ebff",
    "progress.background":"#706383",
    "progressBar.background": "#aa75f5",
    "dropdown.background": "#372f42",
    "dropdown.foreground": "#f3ebff",
    "dropdown.border": "#2a2433",
    "button.background": "#8f51e6",
    "button.hoverBackground": "#9d63ee",
    "button.foreground": "#f3ebff",
    "welcomePage.buttonBackground": "#1e1b22",
    "welcomePage.buttonHoverBackground": "#1e1b22",
    "list.activeSelectionBackground": "#574b68BF",
    "list.activeSelectionForeground":  "#e4d2fe",
    "list.focusBackground": "#372f42",
    "list.focusForeground": "#fc8983",
    "list.hoverBackground": "#372f42",
    "list.hoverForeground": "#fc8983",
    "list.inactiveSelectionBackground": "#372f42",
    "list.inactiveSelectionForeground": "#857897",
    "list.dropBackground": "#f8797240",
    "list.highlightForeground": "#fc8983",
    "list.errorForeground": "#b886fd",
    "list.warningForeground": "#b886fd",
    "list.invalidItemForeground": "#b886fd",
    "gitDecoration.addedResourceForeground": "#d6b9fe",
    "gitDecoration.modifiedResourceForeground": "#f87972",
    "gitDecoration.untrackedResourceForeground": "#fbf9f9",
    "gitDecoration.deletedResourceForeground": "#cf504a",
    "gitDecoration.ignoredResourceForeground": "#574b68",
    "gitDecoration.conflictingResourceForeground": "#aa75f5",
    "scrollbar.shadow": "#1e1b22",
    "scrollbarSlider.activeBackground": "#635775",
    "scrollbarSlider.background": "#372f42",
    "scrollbarSlider.hoverBackground":  "#574b68",
    "editorGutter.background": "#1e1b2264",
    "editorGutter.modifiedBackground": "#aa75f5",
    "editorGutter.addedBackground": "#372f42",
    "editorGutter.deletedBackground": "#cf504a",
    "diffEditor.insertedTextBackground": "#8f51e6",
    "diffEditor.insertedTextBorder": "#8f51e6",
    "diffEditor.removedTextBackground": "#8f51e6",
    "diffEditor.removedTextBorder": "#8f51e6",
    "editorWidget.background": "#1e1b22",
    "editorWidget.border": "#1e1b22",
    "editorSuggestWidget.background": "#372f42",
    "editorSuggestWidget.border":  "#1e1b22",
    "editorSuggestWidget.foreground": "#d7cccb",
    "editorSuggestWidget.highlightForeground": "#ffb6b3",
    "editorSuggestWidget.selectedBackground": "#1e1b22",
    "editorHoverWidget.background": "#1e1b22",
    "editorHoverWidget.border":  "#1e1b22",
    "debugExceptionWidget.background": "#1e1b22",
    "debugExceptionWidget.border": "#1e1b22",
    "editor.background": "#2a2433",
    "editor.foreground": "#afa7b9",
    "editorLineNumber.foreground":"#574b68E6",
    "editorLineNumber.activeForeground": "#9a90a7",
    "editorCursor.foreground": "#b886fd",
    "editorCursor.background": "#2a2433",
    "editorWhitespace.foreground": "#706383",
    "editor.lineHighlightBackground": "#372f42",
    "editor.lineHighlightBorder": null,
    "editorLink.activeForeground": null,
    "editor.rangeHighlightBackground": "#372f42",
    "editor.selectionBackground": "#372f42",
    "editor.selectionHighlightBackground": "#372f42",
    "editor.inactiveSelectionBackground":  "#706383",
    "editorIndentGuide.background": "#372f42",
    "editorIndentGuide.activeBackground": "#574b68",
    "editorRuler.foreground": "#afa7b9",
    "editorCodeLens.foreground": "#afa7b9",
    "editorMarkerNavigation.background": "#372f42",
    "editorMarkerNavigationError.background": "#8f51e6",
    "editorMarkerNavigationWarning.background": "#aa75f5",
    "editor.findMatchBackground": "#574b6880",
    "editor.findMatchHighlightBackground": "#63577580",
    "editor.findRangeHighlightBackground": null,
    "editor.hoverHighlightBackground": "#574b68",
    "editor.wordHighlightBackground": "#372f42",
    "editor.wordHighlightStrongBackground": "#372f42",
    "editorBracketMatch.background": "#1e1b22",
    "editorBracketMatch.border": "#706383",
    "editorOverviewRuler.currentContentForeground": "#b886fd",
    "editorOverviewRuler.incomingContentForeground": "#b886fd",
    "editorOverviewRuler.commonContentForeground": "#b886fd",
    "editorError.foreground": "#9d63ee",
    "editorError.border": null,
    "editorWarning.foreground": "#aa75f5",
    "editorWarning.border": null,
    "peekViewEditor.background": "#2a2433",
    "peekView.border": "#372f42",
    "peekViewEditor.matchHighlightBackground": "#8f51e6",
    "peekViewResult.background": "#2a2433",
    "peekViewResult.fileForeground": "#9a90a7",
    "peekViewResult.lineForeground": "#635775",
    "peekViewResult.matchHighlightBackground": "#8f51e6",
    "peekViewResult.selectionBackground": "#372f42",
    "peekViewResult.selectionForeground": "#afa7b9",
    "peekViewTitle.background": "#1e1b22",
    "peekViewTitleDescription.foreground": "#857897",
    "peekViewTitleLabel.foreground": "#9a90a7",
    "merge.currentHeaderBackground": "#706383",
    "merge.currentContentBackground": null,
    "merge.incomingHeaderBackground": "#9d63ee",
    "merge.incomingContentBackground": null,
    "merge.border": null,
    "editorGroup.background": "#706383",
    "editorGroup.border": "#1e1b22",
    "editorGroup.dropBackground": "#f8797240",
    "editorGroupHeader.tabsBackground": "#372f42",
    "editorGroupHeader.noTabsBackground": "#372f42",
    "editorGroupHeader.tabsBorder": "#1e1b22",
    "tab.activeForeground": "#f3ebff",
    "tab.activeBackground": "#2a2433",
    "tab.inactiveForeground": "#857897",
    "tab.unfocusedActiveForeground": "#857897",
    "tab.unfocusedInactiveForeground": "#857897",
    "tab.inactiveBackground": "#372f42",
    "tab.border": "#2a2433",
    "tab.activeBorder": "#1e1b22",
    "tab.hoverBackground": "#2a2433",
    "tab.unfocusedActiveBorder": "#857897",
    "breadcrumbPicker.background": "#1e1b22",
    "activityBar.background": "#372f42",
    "activityBar.foreground": "#afa7b9",
    "activityBar.border": "#2a2433",
    "activityBar.dropBackground": "#c7a0fe40",
    "activityBarBadge.background": "#8f51e6",
    "activityBarBadge.foreground": "#f3ebff",
    "panel.background": "#1e1b22",
    "panel.border": "#1e1b22",
    "panelTitle.activeBorder": "#635775",
    "panelTitle.activeForeground": "#f3ebff",
    "panelTitle.inactiveForeground": "#857897",
    "panel.dropBackground": "#c7a0fe40",
    "sideBar.background": "#1e1b22",
    "sideBar.foreground": "#857897",
    "sideBarTitle.foreground": "#afa7b9",
    "sideBarSectionHeader.background": "#372f42",
    "sideBarSectionHeader.foreground": "#afa7b9",
    "sideBar.border": "#2a243380",
    "sideBar.dropBackground": "#c7a0fe40",
    "statusBar.foreground": "#706383",
    "statusBar.background": "#2a2433",
    "statusBar.border": "#372f42",
    "statusBar.debuggingBackground": "#2a2433",
    "statusBar.debuggingForeground": null,
    "statusBar.debuggingBorder": "#2a2433",
    "statusBar.noFolderBackground": "#2a2433",
    "statusBar.noFolderForeground": null,
    "statusBar.noFolderBorder": "#372f42",
    "statusBarItem.prominentBackground": "#372f42",
    "statusBarItem.prominentHoverBackground": "#372f42",
    "statusBarItem.activeBackground": "#706383",
    "statusBarItem.hoverBackground": "#372f42",
    "titleBar.activeBackground": "#2a2433",
    "titleBar.activeForeground": "#e4d2fe",
    "titleBar.inactiveBackground": "#1e1b22",
    "titleBar.inactiveForeground": null,
    "notifications.background": "#1e1b22",
    "notifications.foreground": "#e4d2fe",
    "notificationLink.foreground": "#f87972",
    "extensionButton.prominentBackground": "#8f51e6",
    "extensionButton.prominentHoverBackground": "#8f51e6",
    "extensionButton.prominentForeground": "#f3ebff",
    "pickerGroup.foreground": "#e4d2fe",
    "pickerGroup.border": "#1e1b22",
    "debugToolBar.background": "#1e1b22",
    "debugToolBar.border": "#2a2433",
    "walkThrough.embeddedEditorBackground": "#1e1b22",
    "source.elm": "#706383",
    "string.quoted.single.js": "#ffb6b3",
    "meta.objectliteral.js": "#9d63ee",
    "terminal.background": "#1e1b22",
    "terminal.foreground": "#afa7b9",
    "terminalCursor.foreground": "#9d63ee",
    "terminalCursor.background": "#2a2433",
    "terminal.ansiBlack": "#372f42",
    "terminal.ansiRed": "#8f51e6",
    "terminal.ansiGreen": "#8f51e6",
    "terminal.ansiYellow": "#aa75f5",
    "terminal.ansiBlue": "#aa75f5",
    "terminal.ansiMagenta": "#b886fd",
    "terminal.ansiCyan": "#f87972",
    "terminal.ansiWhite": "#e4d2fe",
    "terminal.ansiBrightBlack": "#706383",
    "terminal.ansiBrightRed": "#8d8281",
    "terminal.ansiBrightGreen": "#706383",
    "terminal.ansiBrightYellow": "#857897",
    "terminal.ansiBrightBlue": "#9a90a7",
    "terminal.ansiBrightMagenta": "#9d63ee",
    "terminal.ansiBrightCyan": "#afa7b9",
    "terminal.ansiBrightWhite": "#f3ebff"
  }
}

